easy_requests/__init__.py
easy_requests/__main__.py
easy_requests/cache.py
easy_requests/connections.py
easy_reqeusts-1.1.3.dist-info/METADATA
easy_reqeusts-1.1.3.dist-info/WHEEL
easy_reqeusts-1.1.3.dist-info/top_level.txt
easy_reqeusts-1.1.3.dist-info/RECORD
