Metadata-Version: 2.4
Name: easy-reqeusts
Version: 1.1.3
Summary: A Python library for easiest HTTP requests, handling automatic retries, browser-like headers and built on the official `requests` library for reliability.
Author-email: Cybertest12 <cyber.test@proton.me>
Project-URL: Homepage, https://github.com/Cybertest12/
Project-URL: Issues, https://github.com/Cybertest12/
Classifier: Programming Language :: Python :: 3
Classifier: Operating System :: POSIX :: Linux
Requires-Python: >=3.10
Requires-Dist: requests~=2.32.4
